squeel/__init__.py
squeel/cli.py
squeel/format.py
squeel/format_files.py
squeel/utils.py
squeel-1.1.0.dist-info/LICENSE
squeel-1.1.0.dist-info/METADATA
squeel-1.1.0.dist-info/WHEEL
squeel-1.1.0.dist-info/entry_points.txt
squeel-1.1.0.dist-info/RECORD
