Metadata-Version: 2.1
Name: squeel
Version: 1.1.0
Summary: Format embedded sql (squeel) in python source code files
Author: Ole-Jakob Olsen
Author-email: ole.jakob.olsen@gmail.com
Requires-Python: >=3.9,<4.0
Classifier: Programming Language :: Python :: 3
Classifier: Programming Language :: Python :: 3.9
Classifier: Programming Language :: Python :: 3.10
Classifier: Programming Language :: Python :: 3.11
Classifier: Programming Language :: Python :: 3.12
Requires-Dist: sqlparse (>=0.5.3,<0.6.0)
Requires-Dist: tree_sitter (>=0.23.2,<0.24.0)
Requires-Dist: tree_sitter_python (>=0.23.5,<0.24.0)
